pysigfig/__init__.py
pysigfig/functions.py
pysigfig/number.py
pysigfig-0.0.2.dist-info/LICENSE
pysigfig-0.0.2.dist-info/METADATA
pysigfig-0.0.2.dist-info/WHEEL
pysigfig-0.0.2.dist-info/top_level.txt
pysigfig-0.0.2.dist-info/RECORD
