Metadata-Version: 2.1
Name: pysigfig
Version: 0.0.2
Summary: A package for creating and manipulating floating point numbers accounting for significant figures
Home-page: https://github.com/bertcarnell/pysigfig
Author: Rob Carnell
Author-email: bertcarnell@gmail.com
License: MIT
Keywords: python,significant,chemistry,physics
Platform: UNKNOWN
Classifier: Programming Language :: Python :: 3
Classifier: License :: OSI Approved :: MIT License
Classifier: Operating System :: OS Independent
Requires-Python: >=3.6
Requires-Dist: numpy (==1.19.2)
